eval_type_backport/__init__.py
eval_type_backport/eval_type_backport.py
eval_type_backport/py.typed
eval_type_backport/version.py
eval_type_backport-0.2.1.dist-info/LICENSE.txt
eval_type_backport-0.2.1.dist-info/METADATA
eval_type_backport-0.2.1.dist-info/WHEEL
eval_type_backport-0.2.1.dist-info/top_level.txt
eval_type_backport-0.2.1.dist-info/RECORD
