Metadata-Version: 2.1
Name: eval_type_backport
Version: 0.2.1
Summary: Like `typing._eval_type`, but lets older Python versions use newer typing features.
Home-page: https://github.com/alexmojaki/eval_type_backport
Author: Alex Hall
Author-email: alex.mojaki@gmail.com
License: MIT
Classifier: License :: OSI Approved :: MIT License
Classifier: Programming Language :: Python
Classifier: Programming Language :: Python :: 3
Classifier: Programming Language :: Python :: 3.8
Classifier: Programming Language :: Python :: 3.9
Classifier: Programming Language :: Python :: 3.10
Classifier: Programming Language :: Python :: 3.11
Classifier: Programming Language :: Python :: 3.12
Requires-Python: >=3.8
License-File: LICENSE.txt
Provides-Extra: tests
Requires-Dist: pytest; extra == "tests"
